qlikEngine/QlikWebSocket.py
qlikEngine/__init__.py
qlikEngineConnect-1.0.0.dist-info/METADATA
qlikEngineConnect-1.0.0.dist-info/WHEEL
qlikEngineConnect-1.0.0.dist-info/top_level.txt
qlikEngineConnect-1.0.0.dist-info/RECORD
