Metadata-Version: 2.1
Name: qlikEngineConnect
Version: 1.0.0
Summary: Web-socket connector for Qlik engine API. 
Home-page: https://github.com/PalashPandey/qlik-engine-api-connector/
Author: Palash Pandey
Author-email: pp535@drexel.edu
License: MIT
Platform: UNKNOWN
Classifier: License :: OSI Approved :: MIT License
Classifier: Programming Language :: Python :: 3
Classifier: Programming Language :: Python :: 3.6
Requires-Dist: websocket
Requires-Dist: requests
